termlink/__init__.py
termlink/__main__.py
termlink/adapter.py
termlink/batches.py
termlink/client.py
termlink/codesystem.py
termlink/commands.py
termlink/common.py
termlink/configuration.py
termlink/gsea.py
termlink/hpo.py
termlink/loinc.py
termlink/models.py
termlink/rxnorm.py
termlink/services.py
termlink/snomedct.py
tests/__init__.py
tests/adapter_test.py
tests/client_test.py
tests/codesystem_test.py
tests/common_test.py
tests/configuration_test.py
tests/gsea_test.py
tests/hpo_test.py
tests/models_test.py
tests/rxnorm_test.py
tests/snomedct_test.py
termlink-0.10.1.dist-info/LICENSE.txt
termlink-0.10.1.dist-info/METADATA
termlink-0.10.1.dist-info/WHEEL
termlink-0.10.1.dist-info/top_level.txt
termlink-0.10.1.dist-info/RECORD
