Metadata-Version: 2.1
Name: termlink
Version: 0.10.1
Summary: Provide an ontology via Terminology Service's API link.
Home-page: https://lifeomic.github.io/termlink/
Author: Taylor Steinberg
Author-email: taylor.steinberg@lifeomic.com
License: MIT
Platform: UNKNOWN
Classifier: Development Status :: 3 - Alpha
Classifier: License :: OSI Approved :: MIT License
Classifier: Intended Audience :: Developers
Classifier: Intended Audience :: Healthcare Industry
Classifier: Natural Language :: English
Classifier: Programming Language :: Python
Classifier: Programming Language :: Python :: 3
Classifier: Programming Language :: Python :: 3.7
Classifier: Topic :: Utilities
Requires-Dist: backoff (==1.8.0)
Requires-Dist: dataclasses-json (==0.2.2)
Requires-Dist: petl (==1.2.0)
Requires-Dist: pronto (==0.12.2)
Requires-Dist: ratelimit (==2.2.1)
Requires-Dist: requests (==2.21.0)
Requires-Dist: urllib3 (==1.24.2)
Requires-Dist: validators (==0.12.6)
